SDKPyHardCase/Access.py
SDKPyHardCase/Answer.py
SDKPyHardCase/Question.py
SDKPyHardCase/Survey.py
SDKPyHardCase/User.py
SDKPyHardCase/UserAnswer.py
SDKPyHardCase/__init__.py
SDKPyHardCase-0.0.1.dist-info/METADATA
SDKPyHardCase-0.0.1.dist-info/WHEEL
SDKPyHardCase-0.0.1.dist-info/top_level.txt
SDKPyHardCase-0.0.1.dist-info/RECORD
