Metadata-Version: 2.1
Name: SDKPyHardCase
Version: 0.0.1
Summary: This is the simplest module for work with our SDK
Author: HardCase
Keywords: SDK HardCase
Classifier: Programming Language :: Python :: 3.11
Classifier: License :: OSI Approved :: MIT License
Classifier: Operating System :: OS Independent
Requires-Python: >=3.11
Requires-Dist: typing
Requires-Dist: enum
